README
setup.py
py_descriptive_statistics/__init__.py
py_descriptive_statistics.egg-info/PKG-INFO
py_descriptive_statistics.egg-info/SOURCES.txt
py_descriptive_statistics.egg-info/dependency_links.txt
py_descriptive_statistics.egg-info/not-zip-safe
py_descriptive_statistics.egg-info/top_level.txt