Metadata-Version: 1.0
Name: py-descriptive-statistics
Version: 0.2
Summary: Descriptive Statistcs for Python - simple library that implements mean, variance, std deviation, percentile over lists of numbers
Home-page: https://github.com/gleicon/py_descriptive_statistics
Author: Gleicon Moraes
Author-email: gleicon@gmail.com
License: UNKNOWN
Keywords: descriptive statistics enum mean percentile standard deviation variance stats metrics
Platform: UNKNOWN
